setup.py
OverseerPythonAPI/__init__.py
OverseerPythonAPI.egg-info/PKG-INFO
OverseerPythonAPI.egg-info/SOURCES.txt
OverseerPythonAPI.egg-info/dependency_links.txt
OverseerPythonAPI.egg-info/top_level.txt