Metadata-Version: 1.0
Name: OverseerPythonAPI
Version: 1.0
Summary: API for working with Overseer platform for Python
Home-page: UNKNOWN
Author: TRTGames
Author-email: theredtie.games@gmail.com
License: Free to use
Platform: UNKNOWN
